ai_cli/__init__.py
ai_cli/default_config.yaml
ai_cli/main.py
ai_cli/ollama_client.py
ai_cli/storage.py
kpihx_ai_cli-0.3.6.dist-info/METADATA
kpihx_ai_cli-0.3.6.dist-info/WHEEL
kpihx_ai_cli-0.3.6.dist-info/entry_points.txt
kpihx_ai_cli-0.3.6.dist-info/licenses/LICENSE
kpihx_ai_cli-0.3.6.dist-info/RECORD
