Metadata-Version: 2.4
Name: kpihx-ai-cli
Version: 0.3.6
Summary: Un client CLI intelligent pour Ollama avec gestion d'historique et mémoire persistante
Project-URL: Homepage, https://github.com/KpihX/ai-cli
Project-URL: Repository, https://github.com/KpihX/ai-cli
Project-URL: Issues, https://github.com/KpihX/ai-cli/issues
Author-email: KAMDEM POUOKAM Ivann Harold <kapoivha@gmail.com>
License-Expression: MIT
License-File: LICENSE
Keywords: ai,chatbot,cli,llm,ollama,terminal
Classifier: Development Status :: 4 - Beta
Classifier: Environment :: Console
Classifier: Intended Audience :: Developers
Classifier: License :: OSI Approved :: MIT License
Classifier: Programming Language :: Python :: 3
Classifier: Programming Language :: Python :: 3.11
Classifier: Programming Language :: Python :: 3.12
Classifier: Topic :: Scientific/Engineering :: Artificial Intelligence
Requires-Python: >=3.11
Requires-Dist: prompt-toolkit>=3.0.52
Requires-Dist: pyyaml>=6.0.3
Requires-Dist: requests>=2.32.5
Requires-Dist: rich>=14.2.0
Requires-Dist: typer>=0.21.1
